{"code": 0, "msg": "Success", "data": [{"time": 1651141380, "title": "\u5341\u4e07\u7ea77\u5ea7\u5bb6\u7528\u8f66\u65b0\u6807\u6746 \u4e94\u83f1\u4f73\u8fb0\u662f\u5982\u4f55\u505a\u5230\u7684\uff1f", "link": "https://m.mydrivers.com/newsview/829231.html", "images": ["https://img1.mydrivers.com/img/20220428/e672f438cacb41f2b45ac4797c884ae3.jpg", "https://img1.mydrivers.com/img/20220428/0947fb8676874ef4b6949fd17a6dedf0.jpg", "https://img1.mydrivers.com/img/20220428/745f5c5d5c144b9bb466e10e741286c9.jpg"], "target": "\u5feb\u79d1\u6280"}, {"time": 1651001160, "title": "\u534e\u4e3a\u80e1\u539a\u5d11\uff1a\u6ca1\u6709\u81ea\u5efa\u82af\u7247\u5382\u8ba1\u5212", "link": "https://m.mydrivers.com/newsview/828867.html", "images": ["https://img1.mydrivers.com/img/20220427/19467f7448b24264822abe3d170b0dec.jpg"], "target": "\u5feb\u79d1\u6280"}, {"time": 1651068600, "title": "\u539f\u753b\u5e08\u60ca\u5230\uff1a\u7206\u706bAI\u771f\u628a\u68a6\u5883\u753b\u6210\u73b0\u5b9e\u4e86\uff01\u4e0b\u8f7dAPP\u4eba\u4eba\u53ef\u7528", "link": "https://m.mydrivers.com/newsview/829019.html", "images": ["https://img1.mydrivers.com/img/20220427/0097c9a798ec41bf8066a041d561221b.jpg"], "target": "\u5feb\u79d1\u6280"}, {"time": 1651142160, "title": "\u53c8\u4e00\u56fd\u4ea7\u65b0\u673a\u6838\u5fc3\u53c2\u6570\u6572\u5b9a\uff0180W\u95ea\u5145 30\u5206\u949f\u6ee1\u8840", "link": "https://m.mydrivers.com/newsview/829237.html", "images": ["https://img1.mydrivers.com/img/20220428/a30aaa51aa6745caa843b069e60a1975.png"], "target": "\u5feb\u79d1\u6280"}, {"time": 1651068960, "title": "\u5510\u4ee3\u624d\u5973\uff01\u4e0a\u5b98\u5a49\u513f\u5893\u5fd7\u9996\u6b21\u9762\u5411\u516c\u4f17\u5c55\u51fa", "link": "https://m.mydrivers.com/newsview/829020.html", "images": ["https://img1.mydrivers.com/img/20220427/40be07c41836492d863bf2c43bad5694.png"], "target": "\u5feb\u79d1\u6280"}, {"time": 1651065780, "title": "\u5b9e\u9a8c\u5ba4\u7206\u71c3\u5b66\u9662\u4e00\u540d\u535a\u58eb\u7814\u7a76\u751f\u70e7\u4f24\uff1a\u8fd9\u6240985\u5927\u5b66\u56de\u5e94", "link": "https://m.mydrivers.com/newsview/829003.html", "images": ["https://img1.mydrivers.com/img/20220427/afd3cdcdae5649aaa926f90e6de483ba.jpg"], "target": "\u5feb\u79d1\u6280"}, {"time": 1651140120, "title": "\u5c0f\u53f7\u9a81\u9f998\u6765\u4e86\uff01\u9a81\u9f997 Gen1\u65b0\u673a\u5165\u7f51", "link": "https://m.mydrivers.com/newsview/829218.html", "images": ["https://img1.mydrivers.com/img/20220428/b2ea93ce15894b96b720025355dd0571.png"], "target": "\u5feb\u79d1\u6280"}, {"time": 1650963480, "title": "\u5c0f\u7c735\u6b3e\u65b0\u65d7\u8230\u673a\u66dd\u5149\uff1a\u6362\u5904\u7406\u5668\u540e\u771f\u9999", "link": "https://m.mydrivers.com/newsview/828630.html", "images": ["https://img1.mydrivers.com/img/20220426/499e7738cf364e4c894424a7ab70be7a.png"], "target": "\u5feb\u79d1\u6280"}, {"time": 1651146540, "title": "\u5c0f\u7c73\u6b63\u5f0f\u52a0\u5165CCC\u8463\u4e8b\u4f1a\uff01\u53d1\u529b\u6570\u5b57\u8f66\u94a5\u5319\u5e94\u7528", "link": "https://m.mydrivers.com/newsview/829261.html", "images": ["https://img1.mydrivers.com/img/20220428/6ca1836e70fe48f393123d5bca8c32fd.png"], "target": "\u5feb\u79d1\u6280"}, {"time": 1651144620, "title": "\u5df4\u83f2\u7279\u91cd\u4ed3\u6bd4\u4e9a\u8fea\u8d5a\u7ffb 14\u5e74510\u4ebf\u5143\uff01\u6301\u80a1\u4ec5\u6b21\u4e8e\u738b\u4f20\u798f\u8868\u54e5", "link": "https://m.mydrivers.com/newsview/829242.html", "images": ["https://img1.mydrivers.com/img/20220428/0c9cfb802ed44255ba83c536fc7601b7.jpg"], "target": "\u5feb\u79d1\u6280"}, {"time": 1651141080, "title": "\u5e95\u85aa\u53ea\u662f\u201c\u4eba\u9053\u5e2e\u52a9\u201d\uff01\u516c\u53f8\u62db\u8058\u79f0\u6ca1\u4eba\u6210\u529f\u9760\u53cc\u4f11\u4e0a\u70ed\u641c", "link": "https://m.mydrivers.com/newsview/829230.html", "images": ["https://img1.mydrivers.com/img/20220428/2b9e9a2dcb5c44cfa1c66c1c84beea16.png"], "target": "\u5feb\u79d1\u6280"}, {"time": 1651145100, "title": "\u624b\u6162\u65e0\uff01\u4e94\u82b3\u658b\u8089\u7cbd4\u679a\u5230\u624b9.9\u5143\uff1a\u8f6f\u7cef\u597d\u53e3\u611f", "link": "https://m.mydrivers.com/newsview/829254.html", "images": ["https://img1.mydrivers.com/img/20220428/07600c5364c2430682c979378f8e6cd5.png"], "target": "\u5feb\u79d1\u6280"}, {"time": 1651144620, "title": "\u624b\u673a\u884c\u4e1a\u4e00\u4ee3\u5377\u738b\u8bde\u751f\uff01\u8981\u666e\u53ca512GB\u5927\u5b58\u50a8", "link": "https://m.mydrivers.com/newsview/829243.html", "images": ["https://img1.mydrivers.com/img/20220428/dde0c90c353c4d539ae30034716d77d5.png"], "target": "\u5feb\u79d1\u6280"}, {"time": 1651062120, "title": "\u642d\u8f7dDM-i\u8d85\u6df7 \u6bd4\u4e9a\u8fea\u65b0SUV\u66dd\u5149\uff1a\u7528\u4e0a\u201c\u4e2d\u56fd\u7ed3\u201d\u5c3e\u706f", "link": "https://m.mydrivers.com/newsview/828990.html", "images": ["https://img1.mydrivers.com/img/20220427/2821c812f2234ea68a8fa5ff337180f3.png"], "target": "\u5feb\u79d1\u6280"}, {"time": 1651062960, "title": "\u65e5\u4ea7\u6700\u5e05SUV\uff01\u5168\u65b0\u7535\u52a8\u8f66Ariya\u4e2d\u56fd\u5f00\u5356\uff1a25\u4e07\u4e70\u5417\uff1f", "link": "https://m.mydrivers.com/newsview/828992.html", "images": ["https://img1.mydrivers.com/img/20220427/db50a37ce07c49309aab4b086d1e7748.png"], "target": "\u5feb\u79d1\u6280"}, {"time": 1651146120, "title": "\u663e\u5361\u9a71\u52a8\u662f\u600e\u6837\u70bc\u6210\u7684\uff1f\u8001\u53f8\u673aNVIDIA\u63ed\u79d8\uff1a\u8fd9\u4e09\u62db\u77a7\u597d\u4e86", "link": "https://m.mydrivers.com/newsview/829258.html", "images": ["https://img1.mydrivers.com/img/20220428/4bd8951d9ca4489fbeeb74b5ea81e30c.jpg"], "target": "\u5feb\u79d1\u6280"}, {"time": 1651141560, "title": "\u7279\u65af\u62c9\u5356\u4e8c\u624b\u8fd8\u80fd\u8d5a6\u4e07\uff1f\u8dd1\u4e865\u4e07\u516c\u91cc\u7684\u90a3\u79cd", "link": "https://m.mydrivers.com/newsview/829233.html", "images": ["https://img1.mydrivers.com/img/20220428/394a405a21de4c77a0a4c770a2521b70.png"], "target": "\u5feb\u79d1\u6280"}, {"time": 1651146180, "title": "\u738b\u8005\u8363\u8000\u91cd\u5927\u66f4\u65b0\uff01\u5929\u73919000\u4e4b\u738b\u9996\u53d1\u6781\u9ad8\u5e27\u7387+\u6781\u9650\u753b\u8d28", "link": "https://m.mydrivers.com/newsview/829259.html", "images": ["https://img1.mydrivers.com/img/20220428/12a57f9c97d245a2bbcba27ade8e87dc.png"], "target": "\u5feb\u79d1\u6280"}, {"time": 1651068960, "title": "\u767e\u4e07\u7ea7\u7b2c\u4e8c\u4ee3\u53cc\u82af\u65d7\u8230\uff01vivo X80\u5f00\u7bb1\u56fe\u8d4f", "link": "https://m.mydrivers.com/newsview/829021.html", "images": ["https://img1.mydrivers.com/img/20220427/5075190dd87d41ed9fe2a3dc23f87a52.jpg", "https://img1.mydrivers.com/img/20220427/79a875eaa6d54225b63ff74d87745f5b.jpg", "https://img1.mydrivers.com/img/20220427/620e3a5696e94b54b652de7c0ba49b3a.jpg"], "target": "\u5feb\u79d1\u6280"}, {"time": 1651067280, "title": "\u795e\u79d8\u7684\u6728\u661f\uff1a\u592a\u9633\u7cfb\u7684\u201c\u6076\u9738\u201d \u53ef\u80fd\u8981\u6d88\u5931\u4e86", "link": "https://m.mydrivers.com/newsview/829014.html", "images": ["https://img1.mydrivers.com/img/20220427/2350cdf9874a44829d22d891780ab8dc.png"], "target": "\u5feb\u79d1\u6280"}]}